{
  "summary": {
    "total_generated": 47,
    "total_reference": 78,
    "common_files": 46,
    "generated_only": 1,
    "reference_only": 32
  },
  "common_files": [
    "MstAbility.csv",
    "MstAbilityI18n.csv",
    "MstAdventBattle.csv",
    "MstAdventBattleClearReward.csv",
    "MstAdventBattleI18n.csv",
    "MstAdventBattleRank.csv",
    "MstAdventBattleReward.csv",
    "MstAdventBattleRewardGroup.csv",
    "MstAttack.csv",
    "MstAttackElement.csv",
    "MstAttackI18n.csv",
    "MstEmblem.csv",
    "MstEmblemI18n.csv",
    "MstEnemyCharacter.csv",
    "MstEnemyOutpost.csv",
    "MstEvent.csv",
    "MstEventI18n.csv",
    "MstHomeBanner.csv",
    "MstInGame.csv",
    "MstInGameI18n.csv",
    "MstItem.csv",
    "MstItemI18n.csv",
    "MstKomaLine.csv",
    "MstMissionEvent.csv",
    "MstMissionEventI18n.csv",
    "MstMissionReward.csv",
    "MstPack.csv",
    "MstPackContent.csv",
    "MstPackI18n.csv",
    "MstPvp.csv",
    "MstPvpI18n.csv",
    "MstQuest.csv",
    "MstQuestI18n.csv",
    "MstStage.csv",
    "MstStageI18n.csv",
    "MstStoreProduct.csv",
    "MstStoreProductI18n.csv",
    "MstUnit.csv",
    "MstUnitAbility.csv",
    "MstUnitI18n.csv",
    "OprGacha.csv",
    "OprGachaDisplayUnitI18n.csv",
    "OprGachaI18n.csv",
    "OprGachaPrize.csv",
    "OprGachaUpper.csv",
    "OprGachaUseResource.csv"
  ],
  "generated_only": [
    "MstDailyBonusReward.csv"
  ],
  "reference_only": [
    "MstArtwork.csv",
    "MstArtworkFragment.csv",
    "MstArtworkFragmentI18n.csv",
    "MstArtworkFragmentPosition.csv",
    "MstArtworkI18n.csv",
    "MstAutoPlayerSequence.csv",
    "MstEnemyCharacterI18n.csv",
    "MstEnemyStageParameter.csv",
    "MstEventBonusUnit.csv",
    "MstEventDisplayUnit.csv",
    "MstEventDisplayUnitI18n.csv",
    "MstInGameSpecialRule.csv",
    "MstInGameSpecialRuleUnitStatus.csv",
    "MstMangaAnimation.csv",
    "MstMissionEventDailyBonus.csv",
    "MstMissionEventDailyBonusSchedule.csv",
    "MstMissionEventDependency.csv",
    "MstMissionLimitedTerm.csv",
    "MstMissionLimitedTermI18n.csv",
    "MstPage.csv",
    "MstQuestBonusUnit.csv",
    "MstQuestEventBonusSchedule.csv",
    "MstSpecialAttackI18n.csv",
    "MstSpecialRoleLevelUpAttackElement.csv",
    "MstSpeechBalloonI18n.csv",
    "MstStageClearTimeReward.csv",
    "MstStageEndCondition.csv",
    "MstStageEventReward.csv",
    "MstStageEventSetting.csv",
    "MstUnitSpecificRankUp.csv",
    "OprProduct.csv",
    "OprProductI18n.csv"
  ]
}